gwsumm/__init__.py
gwsumm/__main__.py
gwsumm/_version.py
gwsumm/archive.py
gwsumm/batch.py
gwsumm/channels.py
gwsumm/globalv.py
gwsumm/io.py
gwsumm/mode.py
gwsumm/segments.py
gwsumm/triggers.py
gwsumm/units.py
gwsumm/utils.py
gwsumm/config/__init__.py
gwsumm/config/defaults.ini
gwsumm/config/matplotlib.ini
gwsumm/data/__init__.py
gwsumm/data/coherence.py
gwsumm/data/mathutils.py
gwsumm/data/range.py
gwsumm/data/spectral.py
gwsumm/data/timeseries.py
gwsumm/data/utils.py
gwsumm/html/__init__.py
gwsumm/html/bootstrap.py
gwsumm/html/html5.py
gwsumm/html/static.py
gwsumm/html/tests/__init__.py
gwsumm/html/tests/test_bootstrap.py
gwsumm/html/tests/test_html5.py
gwsumm/html/tests/test_static.py
gwsumm/plot/__init__.py
gwsumm/plot/builtin.py
gwsumm/plot/core.py
gwsumm/plot/mixins.py
gwsumm/plot/noisebudget.py
gwsumm/plot/range.py
gwsumm/plot/registry.py
gwsumm/plot/segments.py
gwsumm/plot/sei.py
gwsumm/plot/utils.py
gwsumm/plot/guardian/__init__.py
gwsumm/plot/guardian/__main__.py
gwsumm/plot/guardian/core.py
gwsumm/plot/guardian/tests/__init__.py
gwsumm/plot/guardian/tests/test_main.py
gwsumm/plot/triggers/__init__.py
gwsumm/plot/triggers/__main__.py
gwsumm/plot/triggers/core.py
gwsumm/plot/triggers/tests/__init__.py
gwsumm/plot/triggers/tests/test_main.py
gwsumm/state/__init__.py
gwsumm/state/all.py
gwsumm/state/core.py
gwsumm/state/registry.py
gwsumm/tabs/__init__.py
gwsumm/tabs/builtin.py
gwsumm/tabs/core.py
gwsumm/tabs/data.py
gwsumm/tabs/etg.py
gwsumm/tabs/fscan.py
gwsumm/tabs/gracedb.py
gwsumm/tabs/guardian.py
gwsumm/tabs/management.py
gwsumm/tabs/misc.py
gwsumm/tabs/registry.py
gwsumm/tabs/sei.py
gwsumm/tabs/stamp.py
gwsumm/tests/__init__.py
gwsumm/tests/common.py
gwsumm/tests/test_archive.py
gwsumm/tests/test_batch.py
gwsumm/tests/test_channels.py
gwsumm/tests/test_config.py
gwsumm/tests/test_data.py
gwsumm/tests/test_mode.py
gwsumm/tests/test_plot.py
gwsumm/tests/test_tabs.py
gwsumm/tests/test_utils.py
gwsumm-2.3.3.dist-info/licenses/LICENSE
gwsumm-2.3.3.dist-info/METADATA
gwsumm-2.3.3.dist-info/WHEEL
gwsumm-2.3.3.dist-info/entry_points.txt
gwsumm-2.3.3.dist-info/top_level.txt
gwsumm-2.3.3.dist-info/RECORD
