Metadata-Version: 2.4
Name: gwsumm
Version: 2.3.3
Summary: A python toolbox used by the LIGO Scientific Collaboration for detector characterisation
Author-email: Alex Urban <alex.urban@ligo.org>, Duncan Macleod <duncan.macleod@ligo.org>
Maintainer-email: Evan Goetz <evan.goetz@ligo.org>
License-Expression: GPL-3.0-or-later
Project-URL: Documentation, https://gwsumm.readthedocs.io
Project-URL: Source Code, https://github.com/gwpy/gwsumm
Project-URL: Bug Tracker, https://github.com/gwpy/gwsumm/issues
Project-URL: Discussion Forum, https://gwdetchar.slack.com
Classifier: Development Status :: 5 - Production/Stable
Classifier: Intended Audience :: Developers
Classifier: Intended Audience :: Science/Research
Classifier: Natural Language :: English
Classifier: Operating System :: OS Independent
Classifier: Programming Language :: Python
Classifier: Programming Language :: Python :: 3
Classifier: Programming Language :: Python :: 3.9
Classifier: Programming Language :: Python :: 3.10
Classifier: Programming Language :: Python :: 3.11
Classifier: Topic :: Scientific/Engineering
Classifier: Topic :: Scientific/Engineering :: Astronomy
Classifier: Topic :: Scientific/Engineering :: Physics
Requires-Python: >=3.9
License-File: LICENSE
Requires-Dist: astropy>=3.0.0
Requires-Dist: gwdatafind>=1.1.1
Requires-Dist: gwdetchar>=2.2.7
Requires-Dist: gwpy>=3.0.9
Requires-Dist: gwtrigfind
Requires-Dist: lalsuite
Requires-Dist: lscsoft-glue>=1.60.0
Requires-Dist: lxml
Requires-Dist: markdown
Requires-Dist: MarkupPy
Requires-Dist: matplotlib>=3.5
Requires-Dist: numpy>=1.16
Requires-Dist: pygments>=2.7.0
Requires-Dist: python-dateutil
Requires-Dist: python-ligo-lw
Requires-Dist: scipy>=1.2.0
Provides-Extra: test
Requires-Dist: flake8; extra == "test"
Requires-Dist: pytest>=3.3.0; extra == "test"
Requires-Dist: pytest-cov>=2.4.0; extra == "test"
Provides-Extra: dev
Requires-Dist: h5py; extra == "dev"
Requires-Dist: ligo-gracedb>=2.0.0; extra == "dev"
Requires-Dist: pykerberos; extra == "dev"
Provides-Extra: doc
Requires-Dist: numpydoc; extra == "doc"
Requires-Dist: sphinx; extra == "doc"
Requires-Dist: sphinx-automodapi; extra == "doc"
Requires-Dist: sphinx_bootstrap_theme; extra == "doc"
Requires-Dist: sphinxcontrib-programoutput; extra == "doc"
Dynamic: license-file
